{
    "Ar36": {
        "error": 2.272167664924797e-07,
        "error_type": "",
        "fit": "previous",
        "references": [
            {
                "exclude": false,
                "record_id": "ba-01-n-11955"
            }
        ],
        "value": -1.963929822268451e-06
    },
    "Ar37": {
        "error": 2.473714105212246e-07,
        "error_type": "",
        "fit": "previous",
        "references": [
            {
                "exclude": false,
                "record_id": "ba-01-n-11955"
            }
        ],
        "value": 1.569037117948402e-07
    },
    "Ar38": {
        "error": 2.750571791487565e-07,
        "error_type": "",
        "fit": "previous",
        "references": [
            {
                "exclude": false,
                "record_id": "ba-01-n-11955"
            }
        ],
        "value": -4.790729028761255e-08
    },
    "Ar39": {
        "error": 2.3490450795584482e-07,
        "error_type": "",
        "fit": "previous",
        "references": [
            {
                "exclude": false,
                "record_id": "ba-01-n-11955"
            }
        ],
        "value": -9.943535726360649e-08
    },
    "Ar40": {
        "error": 2.604580617358375e-06,
        "error_type": "",
        "fit": "previous",
        "references": [
            {
                "exclude": false,
                "record_id": "ba-01-n-11955"
            }
        ],
        "value": 1.0453465661295415e-06
    }
}