{
    "Ar36": {
        "error": 3.8180275717562713e-07,
        "error_type": "",
        "fit": "previous",
        "references": [
            {
                "exclude": false,
                "record_id": "ba-01-n-13308"
            }
        ],
        "value": 2.2989949775321927e-06
    },
    "Ar37": {
        "error": 2.1852178285568929e-07,
        "error_type": "",
        "fit": "previous",
        "references": [
            {
                "exclude": false,
                "record_id": "ba-01-n-13308"
            }
        ],
        "value": -9.058959480439985e-08
    },
    "Ar38": {
        "error": 1.8579427568011486e-07,
        "error_type": "",
        "fit": "previous",
        "references": [
            {
                "exclude": false,
                "record_id": "ba-01-n-13308"
            }
        ],
        "value": 1.244448930810756e-07
    },
    "Ar39": {
        "error": 2.1750321625311446e-07,
        "error_type": "",
        "fit": "previous",
        "references": [
            {
                "exclude": false,
                "record_id": "ba-01-n-13308"
            }
        ],
        "value": 4.7180820216735696e-07
    },
    "Ar40": {
        "error": 2.2227936117092786e-06,
        "error_type": "",
        "fit": "previous",
        "references": [
            {
                "exclude": false,
                "record_id": "ba-01-n-13308"
            }
        ],
        "value": 4.677334642534393e-05
    }
}