{
    "Ar36": {
        "error": 1.0074639014856328e-08,
        "error_type": "",
        "fit": "previous",
        "references": [
            {
                "exclude": false,
                "record_id": "ba-01-n-12615"
            }
        ],
        "value": 4.721274199552391e-07
    },
    "Ar37": {
        "error": 2.2012044244372036e-07,
        "error_type": "",
        "fit": "previous",
        "references": [
            {
                "exclude": false,
                "record_id": "ba-01-n-12615"
            }
        ],
        "value": 5.085215148796846e-08
    },
    "Ar38": {
        "error": 3.2176045144936425e-07,
        "error_type": "",
        "fit": "previous",
        "references": [
            {
                "exclude": false,
                "record_id": "ba-01-n-12615"
            }
        ],
        "value": -2.1827382638340588e-07
    },
    "Ar39": {
        "error": 2.324351747758345e-07,
        "error_type": "",
        "fit": "previous",
        "references": [
            {
                "exclude": false,
                "record_id": "ba-01-n-12615"
            }
        ],
        "value": 1.942060651267865e-07
    },
    "Ar40": {
        "error": 7.62616995815013e-07,
        "error_type": "",
        "fit": "previous",
        "references": [
            {
                "exclude": false,
                "record_id": "ba-01-n-12615"
            }
        ],
        "value": 9.979753311074692e-05
    }
}