{
    "Ar36": {
        "error": 1.2308040969784209e-08,
        "error_type": "",
        "fit": "previous",
        "references": [
            {
                "exclude": false,
                "record_id": "ba-01-n-12206"
            }
        ],
        "value": 4.963432809159718e-07
    },
    "Ar37": {
        "error": 2.3639599024983423e-07,
        "error_type": "",
        "fit": "previous",
        "references": [
            {
                "exclude": false,
                "record_id": "ba-01-n-12206"
            }
        ],
        "value": 6.120238487105331e-07
    },
    "Ar38": {
        "error": 2.3265508503237964e-07,
        "error_type": "",
        "fit": "previous",
        "references": [
            {
                "exclude": false,
                "record_id": "ba-01-n-12206"
            }
        ],
        "value": -6.829565895906115e-07
    },
    "Ar39": {
        "error": 3.0192118720194405e-07,
        "error_type": "",
        "fit": "previous",
        "references": [
            {
                "exclude": false,
                "record_id": "ba-01-n-12206"
            }
        ],
        "value": -3.283410131421096e-07
    },
    "Ar40": {
        "error": 1.299208791697991e-06,
        "error_type": "",
        "fit": "previous",
        "references": [
            {
                "exclude": false,
                "record_id": "ba-01-n-12206"
            }
        ],
        "value": 9.815219934013761e-05
    }
}