{
    "baselines": [
        {
            "blob": "QkgLcbeTGhJCcMJ+t4p+X0KMn5u3eCph",
            "detector": "H3"
        },
        {
            "blob": "QkgLcbhIn8ZCcMJ+uD7pp0KMn5u4Qz8G",
            "detector": "H1"
        },
        {
            "blob": "QkgLcbi0eEpCcMJ+uLYE9UKMn5u4tQIO",
            "detector": "L1"
        },
        {
            "blob": "QkgLcbehl+FCcMJ+t7aQG0KMn5u3sZ8Y",
            "detector": "L3"
        },
        {
            "blob": "QkgLcbwFM0FCcMJ+vAU3LkKMn5u8BT2a",
            "detector": "L5"
        }
    ],
    "commit": "cbbf1b9e80a5c8db868c701c68b2f55e8e18d80a",
    "encoding": "base64",
    "format": ">ff",
    "signals": [
        {
            "blob": "QbmGQz445RdCCN2RPjg/fQ==",
            "detector": "H3",
            "isotope": "Ar40"
        },
        {
            "blob": "QbmGQ7gkxnNCCN2RuAiuNw==",
            "detector": "H1",
            "isotope": "Ar39"
        },
        {
            "blob": "QbmGQzfW7L1CCN2RN89dWg==",
            "detector": "L1",
            "isotope": "Ar38"
        },
        {
            "blob": "QbmGQ7egJYNCCN2Rt55ZFQ==",
            "detector": "L3",
            "isotope": "Ar37"
        },
        {
            "blob": "QbmGQ7v3YYxCCN2Ru/dxyw==",
            "detector": "L5",
            "isotope": "Ar36"
        }
    ],
    "sniffs": [
        {
            "blob": null,
            "detector": "H3",
            "isotope": "Ar40"
        },
        {
            "blob": null,
            "detector": "H1",
            "isotope": "Ar39"
        },
        {
            "blob": null,
            "detector": "L1",
            "isotope": "Ar38"
        },
        {
            "blob": null,
            "detector": "L3",
            "isotope": "Ar37"
        },
        {
            "blob": null,
            "detector": "L5",
            "isotope": "Ar36"
        }
    ]
}