{
    "Ar36": {
        "error": 1.2838314050684893e-08,
        "error_type": "",
        "fit": "previous",
        "references": [
            {
                "exclude": false,
                "record_id": "ba-01-n-12799"
            }
        ],
        "value": 4.863696057382531e-07
    },
    "Ar37": {
        "error": 2.671700497408785e-07,
        "error_type": "",
        "fit": "previous",
        "references": [
            {
                "exclude": false,
                "record_id": "ba-01-n-12799"
            }
        ],
        "value": 9.269930573816073e-07
    },
    "Ar38": {
        "error": 2.8784539861962494e-07,
        "error_type": "",
        "fit": "previous",
        "references": [
            {
                "exclude": false,
                "record_id": "ba-01-n-12799"
            }
        ],
        "value": 5.433351221722658e-07
    },
    "Ar39": {
        "error": 2.518122351710818e-07,
        "error_type": "",
        "fit": "previous",
        "references": [
            {
                "exclude": false,
                "record_id": "ba-01-n-12799"
            }
        ],
        "value": 3.9380647886297446e-07
    },
    "Ar40": {
        "error": 1.4117320185983454e-06,
        "error_type": "",
        "fit": "previous",
        "references": [
            {
                "exclude": false,
                "record_id": "ba-01-n-12799"
            }
        ],
        "value": 0.00011802769064130535
    }
}