{
    "Ar36": {
        "error": 1.0851752132329637e-08,
        "error_type": "",
        "fit": "previous",
        "references": [
            {
                "exclude": false,
                "record_id": "ba-01-n-13509"
            }
        ],
        "value": 5.455221669678686e-07
    },
    "Ar37": {
        "error": 3.371372666242537e-07,
        "error_type": "",
        "fit": "previous",
        "references": [
            {
                "exclude": false,
                "record_id": "ba-01-n-13509"
            }
        ],
        "value": 4.158449295367048e-07
    },
    "Ar38": {
        "error": 3.9255662068829954e-07,
        "error_type": "",
        "fit": "previous",
        "references": [
            {
                "exclude": false,
                "record_id": "ba-01-n-13509"
            }
        ],
        "value": 3.6561440462689384e-07
    },
    "Ar39": {
        "error": 2.820240011091872e-07,
        "error_type": "",
        "fit": "previous",
        "references": [
            {
                "exclude": false,
                "record_id": "ba-01-n-13509"
            }
        ],
        "value": 1.3881791533475467e-06
    },
    "Ar40": {
        "error": 1.4729922893388437e-06,
        "error_type": "",
        "fit": "previous",
        "references": [
            {
                "exclude": false,
                "record_id": "ba-01-n-13509"
            }
        ],
        "value": 0.0001824119790083661
    }
}