{
    "Ar36": {
        "error": 1.1448517128712892e-08,
        "error_type": "",
        "fit": "previous",
        "references": [
            {
                "exclude": false,
                "record_id": "ba-01-n-12891"
            }
        ],
        "value": 2.80933941513599e-07
    },
    "Ar37": {
        "error": 2.2399786235621287e-07,
        "error_type": "",
        "fit": "previous",
        "references": [
            {
                "exclude": false,
                "record_id": "ba-01-n-12891"
            }
        ],
        "value": 8.947768132075823e-07
    },
    "Ar38": {
        "error": 3.0137906144099923e-07,
        "error_type": "",
        "fit": "previous",
        "references": [
            {
                "exclude": false,
                "record_id": "ba-01-n-12891"
            }
        ],
        "value": 2.603562270067693e-07
    },
    "Ar39": {
        "error": 2.2396845363064082e-07,
        "error_type": "",
        "fit": "previous",
        "references": [
            {
                "exclude": false,
                "record_id": "ba-01-n-12891"
            }
        ],
        "value": 3.7736568135192557e-08
    },
    "Ar40": {
        "error": 1.5003753431201017e-06,
        "error_type": "",
        "fit": "previous",
        "references": [
            {
                "exclude": false,
                "record_id": "ba-01-n-12891"
            }
        ],
        "value": 4.9498033151127046e-05
    }
}