{
    "Ar36": {
        "error": 1.1777814533705077e-08,
        "error_type": "",
        "fit": "previous",
        "references": [
            {
                "exclude": false,
                "record_id": "ba-01-n-12858"
            }
        ],
        "value": 2.918410755304747e-07
    },
    "Ar37": {
        "error": 3.371547866234956e-07,
        "error_type": "",
        "fit": "previous",
        "references": [
            {
                "exclude": false,
                "record_id": "ba-01-n-12858"
            }
        ],
        "value": 3.1073971298963465e-07
    },
    "Ar38": {
        "error": 3.810819257203736e-07,
        "error_type": "",
        "fit": "previous",
        "references": [
            {
                "exclude": false,
                "record_id": "ba-01-n-12858"
            }
        ],
        "value": -3.560977565268534e-07
    },
    "Ar39": {
        "error": 3.137652856889827e-07,
        "error_type": "",
        "fit": "previous",
        "references": [
            {
                "exclude": false,
                "record_id": "ba-01-n-12858"
            }
        ],
        "value": -1.3472492306282812e-06
    },
    "Ar40": {
        "error": 1.1565792974385693e-06,
        "error_type": "",
        "fit": "previous",
        "references": [
            {
                "exclude": false,
                "record_id": "ba-01-n-12858"
            }
        ],
        "value": 4.537042146008044e-05
    }
}