{
    "baselines": [
        {
            "blob": "Qkgl1DWxJThCcL/wNWmI3kKMpkY1s8na",
            "detector": "H3"
        },
        {
            "blob": "Qkgl1LhNwTZCcL/wuE5OmEKMpka4RpI2",
            "detector": "H1"
        },
        {
            "blob": "Qkgl1LizAFZCcL/wuK8dJ0KMpka4r76t",
            "detector": "L1"
        },
        {
            "blob": "Qkgl1LexBHpCcL/wt6R7SUKMpka3nVDA",
            "detector": "L3"
        },
        {
            "blob": "Qkgl1LwCbtRCcL/wvAJcYEKMpka8AmuX",
            "detector": "L5"
        }
    ],
    "commit": "ba6f96fd78811b86a51c7e4517778e801d64482e",
    "encoding": "base64",
    "format": ">ff",
    "signals": [
        {
            "blob": "QbnEfT441hdCCP2ePjgYaA==",
            "detector": "H3",
            "isotope": "Ar40"
        },
        {
            "blob": "QbnEfbgdGWZCCP2et/fZqw==",
            "detector": "H1",
            "isotope": "Ar39"
        },
        {
            "blob": "QbnEfTf3wOBCCP2eN+64Xg==",
            "detector": "L1",
            "isotope": "Ar38"
        },
        {
            "blob": "QbnEfbeMDfVCCP2et5awsQ==",
            "detector": "L3",
            "isotope": "Ar37"
        },
        {
            "blob": "QbnEfbvx2apCCP2eu/HhGg==",
            "detector": "L5",
            "isotope": "Ar36"
        }
    ],
    "sniffs": [
        {
            "blob": null,
            "detector": "H3",
            "isotope": "Ar40"
        },
        {
            "blob": null,
            "detector": "H1",
            "isotope": "Ar39"
        },
        {
            "blob": null,
            "detector": "L1",
            "isotope": "Ar38"
        },
        {
            "blob": null,
            "detector": "L3",
            "isotope": "Ar37"
        },
        {
            "blob": null,
            "detector": "L5",
            "isotope": "Ar36"
        }
    ]
}