{
    "Ar36": {
        "error": 1.497918660754386e-08,
        "error_type": "",
        "fit": "previous",
        "references": [
            {
                "exclude": false,
                "record_id": "ba-01-n-12449"
            }
        ],
        "value": 9.945877822523802e-07
    },
    "Ar37": {
        "error": 3.466333203781e-07,
        "error_type": "",
        "fit": "previous",
        "references": [
            {
                "exclude": false,
                "record_id": "ba-01-n-12449"
            }
        ],
        "value": 5.999232967184607e-07
    },
    "Ar38": {
        "error": 4.145417144177063e-07,
        "error_type": "",
        "fit": "previous",
        "references": [
            {
                "exclude": false,
                "record_id": "ba-01-n-12449"
            }
        ],
        "value": 1.2512698467398616e-07
    },
    "Ar39": {
        "error": 3.8471190873621334e-07,
        "error_type": "",
        "fit": "previous",
        "references": [
            {
                "exclude": false,
                "record_id": "ba-01-n-12449"
            }
        ],
        "value": 7.181080463775926e-07
    },
    "Ar40": {
        "error": 1.5022332654090765e-06,
        "error_type": "",
        "fit": "previous",
        "references": [
            {
                "exclude": false,
                "record_id": "ba-01-n-12449"
            }
        ],
        "value": 0.00030508562533224375
    }
}